gcld3/__init__.py
gcld3/pybind_ext.cpython-36m-darwin.so
gcld3/.dylibs/libprotobuf.23.dylib
gcld3-3.0.13.dist-info/RECORD
gcld3-3.0.13.dist-info/LICENSE
gcld3-3.0.13.dist-info/WHEEL
gcld3-3.0.13.dist-info/top_level.txt
gcld3-3.0.13.dist-info/METADATA
