Metadata-Version: 1.0
Name: gcld3
Version: 3.0.13
Summary: CLD3 is a neural network model for language identification.
Home-page: https://github.com/google/cld3
Author: Rami Al-Rfou
Author-email: rmyeid@google.com
License: UNKNOWN
Platform: UNKNOWN
